qadence2_expressions/__init__.py
qadence2_expressions/collect.py
qadence2_expressions/functions.py
qadence2_expressions/ircompiler.py
qadence2_expressions/operators.py
qadence2_expressions/replace.py
qadence2_expressions/core/__init__.py
qadence2_expressions/core/constructors.py
qadence2_expressions/core/environment.py
qadence2_expressions/core/expression.py
qadence2_expressions/core/support.py
qadence2_expressions/core/utils.py
qadence2_expressions-0.3.0.dist-info/METADATA
qadence2_expressions-0.3.0.dist-info/WHEEL
qadence2_expressions-0.3.0.dist-info/RECORD
