Metadata-Version: 2.4
Name: qadence2-expressions
Version: 0.3.0
Summary: Qadence 2 expressions consisting of symbolic expressions and blocks, i.e. quantum digital, analog, digital-analog and composite gates, together with their logic and engine.
Project-URL: Documentation, https://pqs.pages.pasqal.com/qadence2-expressions/
Project-URL: Issues, https://github.com/pasqal-io/qadence2-expressions/-/issues
Project-URL: Source, https://github.com/pasqal-io/qadence2-expressions
Author-email: Kaonan Micadei <kaonan.micadei@pasqal.com>, Eduardo Maschio <eduardo.maschio@pasqal.com>, Roland Guichard <roland.guichard@pasqal.com>, Pim Venderbosch <pim.venderbosch@pasqal.com>, João Moutinho <joao.moutinho@pasqal.com>
License: Apache 2.0
Keywords: quantum
Classifier: Development Status :: 4 - Beta
Classifier: Programming Language :: Python
Classifier: Programming Language :: Python :: 3.10
Classifier: Programming Language :: Python :: 3.11
Classifier: Programming Language :: Python :: 3.12
Classifier: Programming Language :: Python :: 3.13
Classifier: Programming Language :: Python :: Implementation :: CPython
Classifier: Programming Language :: Python :: Implementation :: PyPy
Requires-Python: >=3.10
Requires-Dist: qadence2-ir>=0.2.0
Provides-Extra: extras
